{
  "id": "unknown",
  "name": "DynamicQA",
  "exported_at": "2025-12-18T07:04:08.815110",
  "data": {
    "id": "ScxzcEQ8rxL3Oxlnn9Q8N",
    "name": "DynamicQA",
    "description": null,
    "layout": {
      "sections": [
        {
          "id": {
            "value": "f4e701ee-b6d6-4ecf-8335-772e4d2b6616"
          },
          "rows": [
            {
              "id": {
                "value": "b7579ad1-bd5a-4b41-8b25-403c6795eff3"
              },
              "appearance": {
                "height": 19
              },
              "widgets": [
                {
                  "id": {
                    "value": "7b159d48-58f3-4df7-8001-1ac2ab14c569"
                  },
                  "title": "New Line Chart",
                  "description": null,
                  "definition": {
                    "lineChart": {
                      "legend": {
                        "isVisible": true,
                        "columns": [],
                        "groupByQuery": true,
                        "placement": "LEGEND_PLACEMENT_AUTO"
                      },
                      "tooltip": {
                        "showLabels": false,
                        "type": "TOOLTIP_TYPE_ALL"
                      },
                      "queryDefinitions": [
                        {
                          "id": "aae0da21-88ed-4d02-a74f-e811261b191c",
                          "query": {
                            "dataprime": {
                              "dataprimeQuery": {
                                "text": "source logs\n| groupby $m.timestamp / 9s as $d['timestamp'] agg count() as $d['count'] \n"
                              },
                              "filters": [],
                              "timeFrame": null
                            }
                          },
                          "seriesNameTemplate": null,
                          "seriesCountLimit": "20",
                          "unit": "UNIT_UNSPECIFIED",
                          "scaleType": "SCALE_TYPE_LINEAR",
                          "name": "Query 1",
                          "isVisible": true,
                          "colorScheme": "classic",
                          "resolution": null,
                          "dataModeType": "DATA_MODE_TYPE_HIGH_UNSPECIFIED",
                          "customUnit": null,
                          "decimal": 2,
                          "hashColors": false,
                          "yAxisMin": null,
                          "yAxisMax": null,
                          "decimalPrecision": false
                        }
                      ],
                      "stackedLine": "STACKED_LINE_UNSPECIFIED",
                      "connectNulls": false
                    }
                  },
                  "appearance": null,
                  "createdAt": null,
                  "updatedAt": null
                }
              ]
            },
            {
              "id": {
                "value": "b6f19cf5-b28f-49ed-9c24-8400c8c8bb9d"
              },
              "appearance": {
                "height": 19
              },
              "widgets": [
                {
                  "id": {
                    "value": "5148a76f-0c77-4dcb-9855-46d5a3236230"
                  },
                  "title": "New heatmap",
                  "description": null,
                  "definition": {
                    "dynamic": {
                      "query": {
                        "logs": {
                          "luceneQuery": {
                            "value": ""
                          },
                          "dataModeType": "DATA_MODE_TYPE_HIGH_UNSPECIFIED",
                          "filters": [],
                          "groupBy": [
                            {
                              "keypath": [
                                "applicationname"
                              ],
                              "scope": "DATASET_SCOPE_LABEL"
                            }
                          ],
                          "aggregation": [
                            {
                              "count": {}
                            }
                          ]
                        }
                      },
                      "timeFrame": null,
                      "interpretation": "INTERPRETATION_UNSPECIFIED",
                      "visualization": {
                        "heatmap": {
                          "valueField": {
                            "keypath": [
                              "count_0"
                            ],
                            "scope": "DATASET_SCOPE_USER_DATA"
                          },
                          "xAxisFields": [
                            {
                              "keypath": [
                                "subsystemname"
                              ],
                              "scope": "DATASET_SCOPE_LABEL"
                            }
                          ],
                          "yAxisFields": [
                            {
                              "keypath": [
                                "applicationname"
                              ],
                              "scope": "DATASET_SCOPE_LABEL"
                            }
                          ],
                          "showNumbers": true,
                          "scaleType": "SCALE_TYPE_LINEAR",
                          "preset": "HEATMAP_COLOR_PRESET_BLUE",
                          "allowAbbreviation": false,
                          "unit": "UNIT_UNSPECIFIED",
                          "customUnit": null,
                          "decimalPrecision": 1,
                          "colorAxisMin": null,
                          "colorAxisMax": null,
                          "tooltip": null
                        }
                      }
                    }
                  },
                  "appearance": null,
                  "createdAt": null,
                  "updatedAt": null
                },
                {
                  "id": {
                    "value": "17f78661-212f-44cb-a353-6de9e30b9ff9"
                  },
                  "title": "New dynamic widget",
                  "description": null,
                  "definition": {
                    "dynamic": {
                      "query": {
                        "logs": {
                          "luceneQuery": {
                            "value": ""
                          },
                          "dataModeType": "DATA_MODE_TYPE_HIGH_UNSPECIFIED",
                          "filters": [],
                          "groupBy": [
                            {
                              "keypath": [
                                "applicationname"
                              ],
                              "scope": "DATASET_SCOPE_LABEL"
                            }
                          ],
                          "aggregation": [
                            {
                              "count": {}
                            }
                          ]
                        }
                      },
                      "timeFrame": null,
                      "interpretation": "INTERPRETATION_UNSPECIFIED",
                      "visualization": {
                        "hexagonBins": {
                          "valueField": {
                            "keypath": [
                              "count_0"
                            ],
                            "scope": "DATASET_SCOPE_USER_DATA"
                          },
                          "categoryFields": [
                            {
                              "keypath": [
                                "applicationname"
                              ],
                              "scope": "DATASET_SCOPE_LABEL"
                            }
                          ],
                          "min": 0,
                          "max": 100,
                          "unit": "UNIT_UNSPECIFIED",
                          "customUnit": null,
                          "thresholdType": "THRESHOLD_TYPE_RELATIVE",
                          "thresholds": [
                            {
                              "from": 0,
                              "color": "var(--c-severity-log-verbose)",
                              "label": null
                            },
                            {
                              "from": 33,
                              "color": "var(--c-severity-log-warning)",
                              "label": null
                            },
                            {
                              "from": 66,
                              "color": "var(--c-severity-log-error)",
                              "label": null
                            }
                          ],
                          "legend": {
                            "isVisible": true,
                            "columns": [],
                            "groupByQuery": true,
                            "placement": "LEGEND_PLACEMENT_AUTO"
                          },
                          "legendBy": "LEGEND_BY_GROUPS",
                          "decimalPrecision": 2,
                          "allowAbbreviation": false
                        }
                      }
                    }
                  },
                  "appearance": null,
                  "createdAt": null,
                  "updatedAt": null
                }
              ]
            },
            {
              "id": {
                "value": "57248373-7742-4630-a503-3389b63161e1"
              },
              "appearance": {
                "height": 19
              },
              "widgets": [
                {
                  "id": {
                    "value": "714abe68-1bb1-4755-812f-3c8257756881"
                  },
                  "title": "Multi line chart",
                  "description": null,
                  "definition": {
                    "dynamic": {
                      "query": {
                        "dataprime": {
                          "dataprimeQuery": {
                            "text": "source logs\n| groupby $m.timestamp / 9s as $d['timestamp'] agg count() as $d['count'], count()*2 as $d['count2']"
                          },
                          "dataModeType": "DATA_MODE_TYPE_HIGH_UNSPECIFIED"
                        }
                      },
                      "timeFrame": null,
                      "interpretation": "INTERPRETATION_UNSPECIFIED",
                      "visualization": {
                        "table": {
                          "columns": [
                            {
                              "field": {
                                "keypath": [
                                  "timestamp"
                                ],
                                "scope": "DATASET_SCOPE_USER_DATA"
                              }
                            },
                            {
                              "field": {
                                "keypath": [
                                  "count"
                                ],
                                "scope": "DATASET_SCOPE_USER_DATA"
                              }
                            },
                            {
                              "field": {
                                "keypath": [
                                  "count2"
                                ],
                                "scope": "DATASET_SCOPE_USER_DATA"
                              }
                            }
                          ],
                          "rules": []
                        }
                      }
                    }
                  },
                  "appearance": null,
                  "createdAt": null,
                  "updatedAt": null
                }
              ]
            },
            {
              "id": {
                "value": "0150f41c-5b3b-4b9b-809c-f2c495481f92"
              },
              "appearance": {
                "height": 19
              },
              "widgets": [
                {
                  "id": {
                    "value": "028b0481-f2c8-49e2-b25c-5a4705212391"
                  },
                  "title": "New dynamic widget",
                  "description": null,
                  "definition": {
                    "dynamic": {
                      "query": {
                        "logs": {
                          "luceneQuery": {
                            "value": ""
                          },
                          "dataModeType": "DATA_MODE_TYPE_HIGH_UNSPECIFIED",
                          "filters": [
                            {
                              "field": null,
                              "operator": {
                                "equals": {
                                  "selection": {
                                    "list": {
                                      "values": [
                                        "17266"
                                      ]
                                    }
                                  }
                                }
                              },
                              "observationField": {
                                "keypath": [
                                  "cx_rum",
                                  "labels",
                                  "company_id"
                                ],
                                "scope": "DATASET_SCOPE_USER_DATA"
                              }
                            }
                          ],
                          "groupBy": [],
                          "aggregation": []
                        }
                      },
                      "timeFrame": null,
                      "interpretation": "INTERPRETATION_UNSPECIFIED",
                      "visualization": {
                        "table": {
                          "columns": [
                            {
                              "field": {
                                "keypath": [
                                  "cx_rum",
                                  "web_vitals_context",
                                  "activationStart"
                                ],
                                "scope": "DATASET_SCOPE_USER_DATA"
                              }
                            },
                            {
                              "field": {
                                "keypath": [
                                  "cx_rum",
                                  "version_metadata"
                                ],
                                "scope": "DATASET_SCOPE_USER_DATA"
                              }
                            },
                            {
                              "field": {
                                "keypath": [
                                  "cx_rum",
                                  "event_context",
                                  "severity"
                                ],
                                "scope": "DATASET_SCOPE_USER_DATA"
                              }
                            },
                            {
                              "field": {
                                "keypath": [
                                  "cx_rum",
                                  "web_vitals_context",
                                  "attribution",
                                  "lcpResourceEntry",
                                  "redirectEnd"
                                ],
                                "scope": "DATASET_SCOPE_USER_DATA"
                              }
                            },
                            {
                              "field": {
                                "keypath": [
                                  "cx_rum",
                                  "labels",
                                  "company_id"
                                ],
                                "scope": "DATASET_SCOPE_USER_DATA"
                              }
                            },
                            {
                              "field": {
                                "keypath": [
                                  "cx_rum",
                                  "device_context",
                                  "userAgent"
                                ],
                                "scope": "DATASET_SCOPE_USER_DATA"
                              }
                            },
                            {
                              "field": {
                                "keypath": [
                                  "cx_rum",
                                  "web_vitals_context",
                                  "attribution",
                                  "eventEntry",
                                  "duration"
                                ],
                                "scope": "DATASET_SCOPE_USER_DATA"
                              }
                            },
                            {
                              "field": {
                                "keypath": [
                                  "cx_rum",
                                  "session_context",
                                  "ip_geoip",
                                  "location_geopoint"
                                ],
                                "scope": "DATASET_SCOPE_USER_DATA"
                              }
                            },
                            {
                              "field": {
                                "keypath": [
                                  "cx_rum",
                                  "labels",
                                  "organization_id"
                                ],
                                "scope": "DATASET_SCOPE_USER_DATA"
                              }
                            }
                          ],
                          "rules": [
                            {
                              "id": {
                                "value": "808fe85b-a59f-40ca-a14b-a5a6ea60dab8"
                              },
                              "name": "severity",
                              "description": "",
                              "ruleScope": {
                                "field": {
                                  "keypath": [
                                    "cx_rum",
                                    "event_context",
                                    "severity"
                                  ],
                                  "scope": "DATASET_SCOPE_USER_DATA"
                                }
                              },
                              "properties": [
                                {
                                  "id": {
                                    "value": "0ee092b4-d196-4884-ba1f-35cdd8a098d3"
                                  },
                                  "definition": {
                                    "thresholds": {
                                      "values": [
                                        {
                                          "from": 0,
                                          "color": "var(--c-severity-log-verbose)",
                                          "label": null
                                        },
                                        {
                                          "from": 2,
                                          "color": "var(--c-severity-log-warning)",
                                          "label": null
                                        },
                                        {
                                          "from": 5,
                                          "color": "var(--c-severity-log-error)",
                                          "label": null
                                        }
                                      ],
                                      "type": "THRESHOLD_TYPE_UNSPECIFIED"
                                    }
                                  }
                                }
                              ]
                            }
                          ]
                        }
                      }
                    }
                  },
                  "appearance": null,
                  "createdAt": null,
                  "updatedAt": null
                }
              ]
            },
            {
              "id": {
                "value": "33f1ad35-15ad-4bb3-bdae-e0dea5354225"
              },
              "appearance": {
                "height": 19
              },
              "widgets": [
                {
                  "id": {
                    "value": "a06f914c-cea6-4eb5-bc2d-87237324e73f"
                  },
                  "title": "New dynamic widget",
                  "description": null,
                  "definition": {
                    "dynamic": {
                      "query": {
                        "metrics": {
                          "promqlQuery": {
                            "value": "up"
                          },
                          "promqlQueryType": "PROM_QL_QUERY_TYPE_INSTANT",
                          "editorMode": "METRICS_QUERY_EDITOR_MODE_BUILDER",
                          "seriesLimitType": "METRICS_SERIES_LIMIT_TYPE_UNSPECIFIED"
                        }
                      },
                      "timeFrame": null,
                      "interpretation": "INTERPRETATION_UNSPECIFIED",
                      "visualization": {
                        "table": {
                          "columns": [
                            {
                              "field": {
                                "keypath": [
                                  "value"
                                ],
                                "scope": "DATASET_SCOPE_USER_DATA"
                              }
                            },
                            {
                              "field": {
                                "keypath": [
                                  "cx_subsystem_name"
                                ],
                                "scope": "DATASET_SCOPE_USER_DATA"
                              }
                            },
                            {
                              "field": {
                                "keypath": [
                                  "cloud_platform"
                                ],
                                "scope": "DATASET_SCOPE_USER_DATA"
                              }
                            },
                            {
                              "field": {
                                "keypath": [
                                  "k8s_cluster_name"
                                ],
                                "scope": "DATASET_SCOPE_USER_DATA"
                              }
                            },
                            {
                              "field": {
                                "keypath": [
                                  "job"
                                ],
                                "scope": "DATASET_SCOPE_USER_DATA"
                              }
                            },
                            {
                              "field": {
                                "keypath": [
                                  "host_name"
                                ],
                                "scope": "DATASET_SCOPE_USER_DATA"
                              }
                            },
                            {
                              "field": {
                                "keypath": [
                                  "server_port"
                                ],
                                "scope": "DATASET_SCOPE_USER_DATA"
                              }
                            },
                            {
                              "field": {
                                "keypath": [
                                  "cloud_account_id"
                                ],
                                "scope": "DATASET_SCOPE_USER_DATA"
                              }
                            },
                            {
                              "field": {
                                "keypath": [
                                  "url_scheme"
                                ],
                                "scope": "DATASET_SCOPE_USER_DATA"
                              }
                            },
                            {
                              "field": {
                                "keypath": [
                                  "host_id"
                                ],
                                "scope": "DATASET_SCOPE_USER_DATA"
                              }
                            },
                            {
                              "field": {
                                "keypath": [
                                  "service_version"
                                ],
                                "scope": "DATASET_SCOPE_USER_DATA"
                              }
                            },
                            {
                              "field": {
                                "keypath": [
                                  "cx_agent_type"
                                ],
                                "scope": "DATASET_SCOPE_USER_DATA"
                              }
                            },
                            {
                              "field": {
                                "keypath": [
                                  "cloud_provider"
                                ],
                                "scope": "DATASET_SCOPE_USER_DATA"
                              }
                            },
                            {
                              "field": {
                                "keypath": [
                                  "service_instance_id"
                                ],
                                "scope": "DATASET_SCOPE_USER_DATA"
                              }
                            },
                            {
                              "field": {
                                "keypath": [
                                  "os_type"
                                ],
                                "scope": "DATASET_SCOPE_USER_DATA"
                              }
                            },
                            {
                              "field": {
                                "keypath": [
                                  "cx_application_name"
                                ],
                                "scope": "DATASET_SCOPE_USER_DATA"
                              }
                            },
                            {
                              "field": {
                                "keypath": [
                                  "cloud_availability_zone"
                                ],
                                "scope": "DATASET_SCOPE_USER_DATA"
                              }
                            },
                            {
                              "field": {
                                "keypath": [
                                  "server_address"
                                ],
                                "scope": "DATASET_SCOPE_USER_DATA"
                              }
                            },
                            {
                              "field": {
                                "keypath": [
                                  "host_image_id"
                                ],
                                "scope": "DATASET_SCOPE_USER_DATA"
                              }
                            },
                            {
                              "field": {
                                "keypath": [
                                  "cloud_region"
                                ],
                                "scope": "DATASET_SCOPE_USER_DATA"
                              }
                            },
                            {
                              "field": {
                                "keypath": [
                                  "service_name"
                                ],
                                "scope": "DATASET_SCOPE_USER_DATA"
                              }
                            },
                            {
                              "field": {
                                "keypath": [
                                  "cx_otel_integration_name"
                                ],
                                "scope": "DATASET_SCOPE_USER_DATA"
                              }
                            },
                            {
                              "field": {
                                "keypath": [
                                  "host_type"
                                ],
                                "scope": "DATASET_SCOPE_USER_DATA"
                              }
                            },
                            {
                              "field": {
                                "keypath": [
                                  "k8s_node_name"
                                ],
                                "scope": "DATASET_SCOPE_USER_DATA"
                              }
                            },
                            {
                              "field": {
                                "keypath": [
                                  "net_host_port"
                                ],
                                "scope": "DATASET_SCOPE_USER_DATA"
                              }
                            },
                            {
                              "field": {
                                "keypath": [
                                  "http_scheme"
                                ],
                                "scope": "DATASET_SCOPE_USER_DATA"
                              }
                            },
                            {
                              "field": {
                                "keypath": [
                                  "net_host_name"
                                ],
                                "scope": "DATASET_SCOPE_USER_DATA"
                              }
                            }
                          ],
                          "rules": [
                            {
                              "id": {
                                "value": "f6fe3575-dd4d-466d-9157-8d29af650f9e"
                              },
                              "name": "New rule",
                              "description": "",
                              "ruleScope": {
                                "fieldType": "FIELD_DATA_TYPE_NUMBER"
                              },
                              "properties": [
                                {
                                  "id": {
                                    "value": "079461b6-6138-44aa-9def-9b919e7a6256"
                                  },
                                  "definition": {
                                    "thresholds": {
                                      "values": [
                                        {
                                          "from": 0,
                                          "color": "var(--c-severity-log-verbose)",
                                          "label": null
                                        },
                                        {
                                          "from": 50,
                                          "color": "var(--c-severity-log-warning)",
                                          "label": null
                                        },
                                        {
                                          "from": 75,
                                          "color": "var(--c-severity-log-error)",
                                          "label": null
                                        }
                                      ],
                                      "type": "THRESHOLD_TYPE_UNSPECIFIED"
                                    }
                                  }
                                }
                              ]
                            }
                          ]
                        }
                      }
                    }
                  },
                  "appearance": null,
                  "createdAt": null,
                  "updatedAt": null
                }
              ]
            }
          ],
          "options": {
            "internal": {}
          }
        }
      ]
    },
    "variables": [],
    "filters": [],
    "relativeTimeFrame": "900s",
    "folderId": {
      "value": "435bad47-2e76-414b-ae05-27cb475f63e9"
    },
    "annotations": [],
    "off": {},
    "slugName": null,
    "variablesV2": [],
    "actions": [],
    "_source_folder_name": "Aviv"
  }
}