{
  "id": "unknown",
  "name": "Krishna <> Learning Session",
  "exported_at": "2025-12-18T07:15:42.493288",
  "data": {
    "id": "3pelwg4fQQkaBt2kAKoQX",
    "name": "Krishna <> Learning Session",
    "description": null,
    "layout": {
      "sections": [
        {
          "id": {
            "value": "ddb308c9-312e-4d28-9d93-2f469e7df530"
          },
          "rows": [
            {
              "id": {
                "value": "28ce245f-9c62-441f-a8fa-c346da90ae68"
              },
              "appearance": {
                "height": 29
              },
              "widgets": [
                {
                  "id": {
                    "value": "dd6e56fa-8e28-4db9-bfe8-20e7ed57db3b"
                  },
                  "title": "New Line Chart",
                  "description": null,
                  "definition": {
                    "lineChart": {
                      "legend": {
                        "isVisible": true,
                        "columns": [],
                        "groupByQuery": true,
                        "placement": "LEGEND_PLACEMENT_AUTO"
                      },
                      "tooltip": {
                        "showLabels": false,
                        "type": "TOOLTIP_TYPE_SINGLE"
                      },
                      "queryDefinitions": [
                        {
                          "id": "4af23c37-c715-45d9-bdeb-8bb7c15cdfad",
                          "query": {
                            "logs": {
                              "luceneQuery": {
                                "value": "coralogix.metadata.applicationName:${applicationName}"
                              },
                              "groupBy": [],
                              "aggregations": [
                                {
                                  "count": {}
                                }
                              ],
                              "filters": [],
                              "groupBys": [
                                {
                                  "keypath": [
                                    "applicationname"
                                  ],
                                  "scope": "DATASET_SCOPE_LABEL"
                                }
                              ],
                              "timeFrame": null
                            }
                          },
                          "seriesNameTemplate": null,
                          "seriesCountLimit": "20",
                          "unit": "UNIT_UNSPECIFIED",
                          "scaleType": "SCALE_TYPE_LINEAR",
                          "name": null,
                          "isVisible": true,
                          "colorScheme": "classic",
                          "resolution": {
                            "interval": null,
                            "bucketsPresented": 96
                          },
                          "dataModeType": "DATA_MODE_TYPE_HIGH_UNSPECIFIED",
                          "customUnit": "",
                          "decimal": 2,
                          "hashColors": null,
                          "yAxisMin": null,
                          "yAxisMax": null,
                          "decimalPrecision": null
                        }
                      ],
                      "stackedLine": "STACKED_LINE_UNSPECIFIED",
                      "connectNulls": null
                    }
                  },
                  "appearance": null,
                  "createdAt": null,
                  "updatedAt": null
                }
              ]
            },
            {
              "id": {
                "value": "a42cfee9-37ab-4278-b225-ec1de815dc61"
              },
              "appearance": {
                "height": 19
              },
              "widgets": [
                {
                  "id": {
                    "value": "66dbd130-9c33-4855-b23c-c473f875d1e6"
                  },
                  "title": "New Line Chart",
                  "description": null,
                  "definition": {
                    "lineChart": {
                      "legend": {
                        "isVisible": true,
                        "columns": [],
                        "groupByQuery": true,
                        "placement": "LEGEND_PLACEMENT_AUTO"
                      },
                      "tooltip": {
                        "showLabels": false,
                        "type": "TOOLTIP_TYPE_ALL"
                      },
                      "queryDefinitions": [
                        {
                          "id": "273d1739-7afb-425a-9b3e-b995330282e3",
                          "query": {
                            "metrics": {
                              "promqlQuery": {
                                "value": "bytes_cx_avg{country =~ 'Canada|Germany|Israel|Japan'}"
                              },
                              "filters": [],
                              "editorMode": "METRICS_QUERY_EDITOR_MODE_TEXT",
                              "timeFrame": null,
                              "seriesLimitType": "METRICS_SERIES_LIMIT_TYPE_UNSPECIFIED"
                            }
                          },
                          "seriesNameTemplate": null,
                          "seriesCountLimit": "20",
                          "unit": "UNIT_UNSPECIFIED",
                          "scaleType": "SCALE_TYPE_LINEAR",
                          "name": "Query 1",
                          "isVisible": true,
                          "colorScheme": "classic",
                          "resolution": {
                            "interval": null,
                            "bucketsPresented": 96
                          },
                          "dataModeType": "DATA_MODE_TYPE_HIGH_UNSPECIFIED",
                          "customUnit": "",
                          "decimal": 2,
                          "hashColors": null,
                          "yAxisMin": null,
                          "yAxisMax": null,
                          "decimalPrecision": null
                        }
                      ],
                      "stackedLine": "STACKED_LINE_UNSPECIFIED",
                      "connectNulls": null
                    }
                  },
                  "appearance": null,
                  "createdAt": null,
                  "updatedAt": null
                }
              ]
            }
          ],
          "options": {
            "internal": {}
          }
        }
      ]
    },
    "variables": [
      {
        "name": "applicationName",
        "definition": {
          "multiSelect": {
            "selected": [],
            "source": {
              "query": {
                "query": {
                  "logsQuery": {
                    "type": {
                      "fieldValue": {
                        "observationField": {
                          "keypath": [
                            "applicationname"
                          ],
                          "scope": "DATASET_SCOPE_LABEL"
                        }
                      }
                    }
                  }
                },
                "refreshStrategy": "REFRESH_STRATEGY_UNSPECIFIED",
                "valueDisplayOptions": {
                  "valueRegex": null,
                  "labelRegex": null
                }
              }
            },
            "selection": {
              "all": {}
            },
            "valuesOrderDirection": "ORDER_DIRECTION_ASC",
            "selectionOptions": {
              "selectionType": "SELECTION_TYPE_MULTI_ALL"
            }
          }
        },
        "displayName": "applicationName",
        "description": null,
        "displayType": "VARIABLE_DISPLAY_TYPE_UNSPECIFIED"
      },
      {
        "name": "k8s_pod_name",
        "definition": {
          "multiSelect": {
            "selected": [],
            "source": {
              "query": {
                "query": {
                  "metricsQuery": {
                    "type": {
                      "labelValue": {
                        "metricName": {
                          "stringValue": "k8s_pod_cpu_utilization_1"
                        },
                        "labelName": {
                          "stringValue": "k8s_pod_name"
                        },
                        "labelFilters": []
                      }
                    }
                  }
                },
                "refreshStrategy": "REFRESH_STRATEGY_UNSPECIFIED",
                "valueDisplayOptions": {
                  "valueRegex": "^coralogix-.*",
                  "labelRegex": null
                }
              }
            },
            "selection": {
              "all": {}
            },
            "valuesOrderDirection": "ORDER_DIRECTION_ASC",
            "selectionOptions": {
              "selectionType": "SELECTION_TYPE_MULTI_ALL"
            }
          }
        },
        "displayName": "k8s_pod_name",
        "description": null,
        "displayType": "VARIABLE_DISPLAY_TYPE_UNSPECIFIED"
      }
    ],
    "filters": [
      {
        "source": {
          "logs": {
            "field": null,
            "operator": {
              "equals": {
                "selection": {
                  "list": {
                    "values": []
                  }
                }
              }
            },
            "observationField": {
              "keypath": [
                "subsystemname"
              ],
              "scope": "DATASET_SCOPE_LABEL"
            }
          }
        },
        "enabled": true,
        "collapsed": false,
        "displayName": null
      }
    ],
    "relativeTimeFrame": "900s",
    "annotations": [
      {
        "id": "ebc24499-fb62-4aa9-b187-94f00838f77f",
        "name": "test",
        "enabled": false,
        "source": {
          "metrics": {
            "promqlQuery": {
              "value": "sum(up) by (job)"
            },
            "strategy": {},
            "messageTemplate": "",
            "labels": [],
            "orientation": "ANNOTATION_ORIENTATION_VERTICAL_UNSPECIFIED"
          }
        },
        "description": null,
        "scope": null,
        "color": "ANNOTATION_COLOR_UNSPECIFIED"
      }
    ],
    "off": {},
    "slugName": null,
    "variablesV2": [],
    "actions": []
  }
}