{
  "id": "unknown",
  "name": "Product KPI Dashboard",
  "exported_at": "2025-12-19T08:57:28.959313",
  "data": {
    "id": "W4bA7zSZ9RV8jW4IbiIVu",
    "name": "Product KPI Dashboard",
    "description": null,
    "layout": {
      "sections": [
        {
          "id": {
            "value": "4ed1d699-06a8-4265-912b-e356eb767737"
          },
          "rows": [
            {
              "id": {
                "value": "366a9cbe-5de9-44a6-a5e8-6b20f7f16a6e"
              },
              "appearance": {
                "height": 19
              },
              "widgets": [
                {
                  "id": {
                    "value": "c7437b7b-ed80-4e2f-81d5-4acfe569ecdf"
                  },
                  "title": "Product Revenue",
                  "description": null,
                  "definition": {
                    "pieChart": {
                      "query": {
                        "dataprime": {
                          "dataprimeQuery": {
                            "text": "source logs\n| lucene 'attributes.productId:\"{{product_id}}\"'\n| filter $d.attributes.productId != null\n| filter $d.attributes.product_details.price_in_currency != null\n| groupby  $d.attributes.productId as $d['attributes.productId'] agg sum($d.attributes.product_details.price_in_currency: number) as $d['sum_attributes.product_details.price_in_currency']"
                          },
                          "filters": [],
                          "groupNames": [
                            "attributes.productId"
                          ],
                          "stackedGroupName": null,
                          "timeFrame": null
                        }
                      },
                      "maxSlicesPerChart": 10,
                      "minSlicePercentage": 1,
                      "stackDefinition": {
                        "maxSlicesPerStack": 4,
                        "stackNameTemplate": null
                      },
                      "labelDefinition": {
                        "labelSource": "LABEL_SOURCE_INNER",
                        "isVisible": true,
                        "showName": true,
                        "showValue": true,
                        "showPercentage": true
                      },
                      "showLegend": true,
                      "groupNameTemplate": null,
                      "unit": "UNIT_UNSPECIFIED",
                      "colorScheme": "classic",
                      "dataModeType": "DATA_MODE_TYPE_ARCHIVE",
                      "customUnit": "",
                      "decimal": null,
                      "legend": {
                        "isVisible": true,
                        "columns": [],
                        "groupByQuery": true,
                        "placement": "LEGEND_PLACEMENT_AUTO"
                      },
                      "hashColors": false,
                      "decimalPrecision": null,
                      "showTotal": null
                    }
                  },
                  "appearance": null,
                  "createdAt": null,
                  "updatedAt": null
                },
                {
                  "id": {
                    "value": "6eed7d38-c8ce-42c8-abec-57e46f4de925"
                  },
                  "title": "Product Count",
                  "description": null,
                  "definition": {
                    "pieChart": {
                      "query": {
                        "logs": {
                          "luceneQuery": {
                            "value": "attributes.productId:\"{{product_id}}\""
                          },
                          "aggregation": {
                            "count": {}
                          },
                          "filters": [],
                          "groupNames": [],
                          "stackedGroupName": null,
                          "groupNamesFields": [
                            {
                              "keypath": [
                                "attributes",
                                "productId"
                              ],
                              "scope": "DATASET_SCOPE_USER_DATA"
                            }
                          ],
                          "stackedGroupNameField": null,
                          "timeFrame": null
                        }
                      },
                      "maxSlicesPerChart": 10,
                      "minSlicePercentage": 1,
                      "stackDefinition": {
                        "maxSlicesPerStack": 4,
                        "stackNameTemplate": null
                      },
                      "labelDefinition": {
                        "labelSource": "LABEL_SOURCE_INNER",
                        "isVisible": true,
                        "showName": true,
                        "showValue": true,
                        "showPercentage": true
                      },
                      "showLegend": true,
                      "groupNameTemplate": null,
                      "unit": "UNIT_UNSPECIFIED",
                      "colorScheme": "classic",
                      "dataModeType": "DATA_MODE_TYPE_ARCHIVE",
                      "customUnit": "",
                      "decimal": null,
                      "legend": {
                        "isVisible": true,
                        "columns": [],
                        "groupByQuery": true,
                        "placement": "LEGEND_PLACEMENT_AUTO"
                      },
                      "hashColors": false,
                      "decimalPrecision": null,
                      "showTotal": null
                    }
                  },
                  "appearance": null,
                  "createdAt": null,
                  "updatedAt": null
                }
              ]
            },
            {
              "id": {
                "value": "270df8f6-8654-473b-a090-a176893a225d"
              },
              "appearance": {
                "height": 19
              },
              "widgets": [
                {
                  "id": {
                    "value": "3e0c40e1-8850-48e3-9d8d-9510e9d7d0bd"
                  },
                  "title": "Revenue by Products",
                  "description": null,
                  "definition": {
                    "gauge": {
                      "query": {
                        "dataprime": {
                          "dataprimeQuery": {
                            "text": "source logs\n| lucene 'attributes.productId:\"{{product_id}}\"'\n| filter $d.attributes.productId != null\n| filter $d.attributes.product_details.price_in_currency != null\n| groupby $d.attributes.productId as $d['attributes.productId'] agg sum($d.attributes.product_details.price_in_currency: number) as $d['sum_attributes.product_details.price_in_currency']"
                          },
                          "filters": [],
                          "timeFrame": null
                        }
                      },
                      "min": 0,
                      "max": 100000,
                      "showInnerArc": false,
                      "showOuterArc": false,
                      "unit": "UNIT_USD",
                      "thresholds": [
                        {
                          "from": 0,
                          "color": "var(--c-severity-log-error)",
                          "label": null
                        },
                        {
                          "from": 100,
                          "color": "var(--c-severity-log-warning)",
                          "label": null
                        },
                        {
                          "from": 1000,
                          "color": "var(--c-severity-log-verbose)",
                          "label": null
                        }
                      ],
                      "dataModeType": "DATA_MODE_TYPE_ARCHIVE",
                      "thresholdBy": "THRESHOLD_BY_VALUE",
                      "customUnit": "",
                      "decimal": 3,
                      "thresholdType": "THRESHOLD_TYPE_ABSOLUTE",
                      "legend": {
                        "isVisible": true,
                        "columns": [],
                        "groupByQuery": true,
                        "placement": "LEGEND_PLACEMENT_AUTO"
                      },
                      "legendBy": "LEGEND_BY_GROUPS",
                      "displaySeriesName": true,
                      "decimalPrecision": null
                    }
                  },
                  "appearance": null,
                  "createdAt": null,
                  "updatedAt": null
                }
              ]
            },
            {
              "id": {
                "value": "e770d341-ecb8-4923-9da1-f60fe04f4ca6"
              },
              "appearance": {
                "height": 19
              },
              "widgets": [
                {
                  "id": {
                    "value": "f63b2ead-f479-4188-8885-92584f756a09"
                  },
                  "title": "Number of Products Sold",
                  "description": null,
                  "definition": {
                    "gauge": {
                      "query": {
                        "dataprime": {
                          "dataprimeQuery": {
                            "text": "source logs\n| lucene 'attributes.productId:\"{{product_id}}\"'\n| filter $d.attributes.productId != null\n| groupby $d.attributes.productId as $d['productId'] agg count() as $d['count']"
                          },
                          "filters": [],
                          "timeFrame": null
                        }
                      },
                      "min": 0,
                      "max": 1000000,
                      "showInnerArc": false,
                      "showOuterArc": false,
                      "unit": "UNIT_NUMBER",
                      "thresholds": [
                        {
                          "from": 0,
                          "color": "var(--c-severity-log-verbose)",
                          "label": null
                        }
                      ],
                      "dataModeType": "DATA_MODE_TYPE_ARCHIVE",
                      "thresholdBy": "THRESHOLD_BY_VALUE",
                      "customUnit": "",
                      "decimal": 3,
                      "thresholdType": "THRESHOLD_TYPE_ABSOLUTE",
                      "legend": {
                        "isVisible": true,
                        "columns": [],
                        "groupByQuery": true,
                        "placement": "LEGEND_PLACEMENT_AUTO"
                      },
                      "legendBy": "LEGEND_BY_GROUPS",
                      "displaySeriesName": true,
                      "decimalPrecision": null
                    }
                  },
                  "appearance": null,
                  "createdAt": null,
                  "updatedAt": null
                }
              ]
            },
            {
              "id": {
                "value": "be5087f9-e014-49f8-9778-87054c386615"
              },
              "appearance": {
                "height": 19
              },
              "widgets": [
                {
                  "id": {
                    "value": "dc08a877-caa7-43f8-a604-fe9b184bbd4a"
                  },
                  "title": "Product Category count",
                  "description": null,
                  "definition": {
                    "barChart": {
                      "query": {
                        "dataprime": {
                          "dataprimeQuery": {
                            "text": "source logs\n| lucene 'attributes.productId:\"{{product_id}}\"'\n| filter $d.attributes.product_details.category != null\n| groupby $d.attributes.product_details.category as $d['attributes.product_details.category'] agg count() as $d['count']"
                          },
                          "filters": [
                            {
                              "logs": {
                                "field": null,
                                "operator": {
                                  "equals": {
                                    "selection": {
                                      "all": {}
                                    }
                                  }
                                },
                                "observationField": {
                                  "keypath": [
                                    "attributes",
                                    "product_details",
                                    "category"
                                  ],
                                  "scope": "DATASET_SCOPE_USER_DATA"
                                }
                              }
                            }
                          ],
                          "groupNames": [
                            "attributes.product_details.category"
                          ],
                          "stackedGroupName": null,
                          "timeFrame": null
                        }
                      },
                      "maxBarsPerChart": 24,
                      "groupNameTemplate": null,
                      "stackDefinition": {
                        "maxSlicesPerBar": 7,
                        "stackNameTemplate": null
                      },
                      "scaleType": "SCALE_TYPE_LINEAR",
                      "colorsBy": {
                        "groupBy": {}
                      },
                      "xAxis": {
                        "value": {}
                      },
                      "unit": "UNIT_UNSPECIFIED",
                      "sortBy": "SORT_BY_TYPE_VALUE",
                      "colorScheme": "classic",
                      "dataModeType": "DATA_MODE_TYPE_ARCHIVE",
                      "barValueDisplay": "BAR_VALUE_DISPLAY_UNSPECIFIED",
                      "customUnit": "",
                      "decimal": 2,
                      "legend": {
                        "isVisible": true,
                        "columns": [],
                        "groupByQuery": true,
                        "placement": "LEGEND_PLACEMENT_SIDE"
                      },
                      "hashColors": false,
                      "yAxisMin": null,
                      "yAxisMax": null,
                      "decimalPrecision": null
                    }
                  },
                  "appearance": null,
                  "createdAt": null,
                  "updatedAt": null
                },
                {
                  "id": {
                    "value": "5290641a-c425-4e70-b18e-e12acb7f951b"
                  },
                  "title": "Product Category count",
                  "description": null,
                  "definition": {
                    "lineChart": {
                      "legend": {
                        "isVisible": true,
                        "columns": [],
                        "groupByQuery": true,
                        "placement": "LEGEND_PLACEMENT_AUTO"
                      },
                      "tooltip": {
                        "showLabels": false,
                        "type": "TOOLTIP_TYPE_ALL"
                      },
                      "queryDefinitions": [
                        {
                          "id": "7682be91-00fe-4855-9340-29c168d95624",
                          "query": {
                            "dataprime": {
                              "dataprimeQuery": {
                                "text": "source logs\n| lucene 'attributes.productId:\"{{product_id}}\"'\n| filter $d.attributes.product_details.category != null\n| groupby $m.timestamp / 4500s as $d['timestamp'], $d.attributes.product_details.category as $d['attributes.product_details.category'] agg count() as $d['count']"
                              },
                              "filters": [
                                {
                                  "logs": {
                                    "field": null,
                                    "operator": {
                                      "equals": {
                                        "selection": {
                                          "all": {}
                                        }
                                      }
                                    },
                                    "observationField": {
                                      "keypath": [
                                        "attributes",
                                        "product_details",
                                        "category"
                                      ],
                                      "scope": "DATASET_SCOPE_USER_DATA"
                                    }
                                  }
                                }
                              ],
                              "timeFrame": null
                            }
                          },
                          "seriesNameTemplate": "{{attributes.product_details.category}}",
                          "seriesCountLimit": "20",
                          "unit": "UNIT_UNSPECIFIED",
                          "scaleType": "SCALE_TYPE_LINEAR",
                          "name": null,
                          "isVisible": true,
                          "colorScheme": "classic",
                          "resolution": null,
                          "dataModeType": "DATA_MODE_TYPE_ARCHIVE",
                          "customUnit": "",
                          "decimal": 2,
                          "hashColors": false,
                          "yAxisMin": null,
                          "yAxisMax": null,
                          "decimalPrecision": null
                        }
                      ],
                      "stackedLine": "STACKED_LINE_UNSPECIFIED",
                      "connectNulls": null
                    }
                  },
                  "appearance": null,
                  "createdAt": null,
                  "updatedAt": null
                }
              ]
            },
            {
              "id": {
                "value": "1bcdacfa-111f-4cfd-bf42-ca02654e2892"
              },
              "appearance": {
                "height": 19
              },
              "widgets": [
                {
                  "id": {
                    "value": "a2ecdde9-a125-4419-9538-84cd622aec2e"
                  },
                  "title": "Product Category Currency",
                  "description": null,
                  "definition": {
                    "barChart": {
                      "query": {
                        "dataprime": {
                          "dataprimeQuery": {
                            "text": "source logs\n| lucene 'attributes.productId:\"{{product_id}}\"'\n| filter $d.attributes.product_details.currency != null\n| groupby $d.attributes.product_details.currency as $d['attributes.product_details.currency'] agg count() as $d['count']"
                          },
                          "filters": [
                            {
                              "logs": {
                                "field": null,
                                "operator": {
                                  "equals": {
                                    "selection": {
                                      "all": {}
                                    }
                                  }
                                },
                                "observationField": {
                                  "keypath": [
                                    "attributes",
                                    "product_details",
                                    "category"
                                  ],
                                  "scope": "DATASET_SCOPE_USER_DATA"
                                }
                              }
                            }
                          ],
                          "groupNames": [
                            "attributes.product_details.currency"
                          ],
                          "stackedGroupName": null,
                          "timeFrame": null
                        }
                      },
                      "maxBarsPerChart": 24,
                      "groupNameTemplate": null,
                      "stackDefinition": {
                        "maxSlicesPerBar": 7,
                        "stackNameTemplate": null
                      },
                      "scaleType": "SCALE_TYPE_LINEAR",
                      "colorsBy": {
                        "groupBy": {}
                      },
                      "xAxis": {
                        "value": {}
                      },
                      "unit": "UNIT_UNSPECIFIED",
                      "sortBy": "SORT_BY_TYPE_VALUE",
                      "colorScheme": "classic",
                      "dataModeType": "DATA_MODE_TYPE_ARCHIVE",
                      "barValueDisplay": "BAR_VALUE_DISPLAY_UNSPECIFIED",
                      "customUnit": "",
                      "decimal": 2,
                      "legend": {
                        "isVisible": true,
                        "columns": [],
                        "groupByQuery": true,
                        "placement": "LEGEND_PLACEMENT_SIDE"
                      },
                      "hashColors": false,
                      "yAxisMin": null,
                      "yAxisMax": null,
                      "decimalPrecision": null
                    }
                  },
                  "appearance": null,
                  "createdAt": null,
                  "updatedAt": null
                },
                {
                  "id": {
                    "value": "6ad487bf-d221-46a6-8f4a-731f8438f11f"
                  },
                  "title": "Product Category Currency",
                  "description": null,
                  "definition": {
                    "lineChart": {
                      "legend": {
                        "isVisible": true,
                        "columns": [],
                        "groupByQuery": true,
                        "placement": "LEGEND_PLACEMENT_AUTO"
                      },
                      "tooltip": {
                        "showLabels": false,
                        "type": "TOOLTIP_TYPE_ALL"
                      },
                      "queryDefinitions": [
                        {
                          "id": "4111a563-8f36-4dc4-8042-871903fef3d8",
                          "query": {
                            "dataprime": {
                              "dataprimeQuery": {
                                "text": "source logs\n| lucene 'attributes.productId:\"{{product_id}}\"'\n| filter $d.attributes.product_details.currency != null\n| groupby $m.timestamp / 4500s as $d['timestamp'], $d.attributes.product_details.currency as $d['attributes.product_details.currency'] agg count() as $d['count']"
                              },
                              "filters": [
                                {
                                  "logs": {
                                    "field": null,
                                    "operator": {
                                      "equals": {
                                        "selection": {
                                          "all": {}
                                        }
                                      }
                                    },
                                    "observationField": {
                                      "keypath": [
                                        "attributes",
                                        "product_details",
                                        "category"
                                      ],
                                      "scope": "DATASET_SCOPE_USER_DATA"
                                    }
                                  }
                                }
                              ],
                              "timeFrame": null
                            }
                          },
                          "seriesNameTemplate": "{{attributes.product_details.currency}}",
                          "seriesCountLimit": "20",
                          "unit": "UNIT_UNSPECIFIED",
                          "scaleType": "SCALE_TYPE_LINEAR",
                          "name": null,
                          "isVisible": true,
                          "colorScheme": "classic",
                          "resolution": null,
                          "dataModeType": "DATA_MODE_TYPE_ARCHIVE",
                          "customUnit": "",
                          "decimal": 2,
                          "hashColors": false,
                          "yAxisMin": null,
                          "yAxisMax": null,
                          "decimalPrecision": null
                        }
                      ],
                      "stackedLine": "STACKED_LINE_UNSPECIFIED",
                      "connectNulls": null
                    }
                  },
                  "appearance": null,
                  "createdAt": null,
                  "updatedAt": null
                }
              ]
            },
            {
              "id": {
                "value": "1522f6fc-2220-4f1c-82d6-8bc78ece5c91"
              },
              "appearance": {
                "height": 29
              },
              "widgets": [
                {
                  "id": {
                    "value": "95fdf272-74ec-4b92-9f44-cffc5809edb3"
                  },
                  "title": "New Markdown",
                  "description": null,
                  "definition": {
                    "markdown": {
                      "markdownText": "![](https://www.coralogix-demo.net/static/img/products/watch.jpg) ![](https://www.coralogix-demo.net/static/img/products/candle-holder.jpg)\n![](https://www.coralogix-demo.net/static/img/products/hairdryer.jpg) ![](https://www.coralogix-demo.net/static/img/products/sunglasses.jpg) \n![](https://www.coralogix-demo.net/static/img/products/bamboo-glass-jar.jpg)\n",
                      "tooltipText": null
                    }
                  },
                  "appearance": null,
                  "createdAt": null,
                  "updatedAt": null
                }
              ]
            }
          ],
          "options": {
            "internal": {}
          }
        }
      ]
    },
    "variables": [
      {
        "name": "product_id",
        "definition": {
          "multiSelect": {
            "selected": [],
            "source": {
              "query": {
                "query": {
                  "logsQuery": {
                    "type": {
                      "fieldValue": {
                        "observationField": {
                          "keypath": [
                            "attributes",
                            "productId"
                          ],
                          "scope": "DATASET_SCOPE_USER_DATA"
                        }
                      }
                    }
                  }
                },
                "refreshStrategy": "REFRESH_STRATEGY_UNSPECIFIED",
                "valueDisplayOptions": {
                  "valueRegex": null,
                  "labelRegex": null
                }
              }
            },
            "selection": {
              "all": {}
            },
            "valuesOrderDirection": "ORDER_DIRECTION_ASC",
            "selectionOptions": {
              "selectionType": "SELECTION_TYPE_MULTI_ALL"
            }
          }
        },
        "displayName": "product_id",
        "description": null,
        "displayType": "VARIABLE_DISPLAY_TYPE_UNSPECIFIED"
      }
    ],
    "filters": [],
    "relativeTimeFrame": "21600s",
    "folderId": null,
    "folderPath": null,
    "annotations": [],
    "off": {},
    "slugName": null,
    "variablesV2": [],
    "actions": []
  }
}